astroget/Results.py
astroget/__init__.py
astroget/client.py
astroget/exceptions.py
astroget/experimental.py
astroget/foo.py
astroget/utils.py
astroget-0.0.3.dist-info/METADATA
astroget-0.0.3.dist-info/WHEEL
astroget-0.0.3.dist-info/licenses/LICENSE
astroget-0.0.3.dist-info/RECORD
