Metadata-Version: 2.1
Name: astroget
Version: 0.0.3
Summary: Find and get FITS metadata and images.
Project-URL: Homepage, https://github.com/pypa/astroget
Project-URL: Bug Tracker, https://github.com/pypa/astroget/issues
Project-URL: Documentation, https://astroget.readthedocs.io/en/latest/
Author-email: "S. Pothier" <astroarchive@noirlab.edu>
License-File: LICENSE
Classifier: License :: OSI Approved :: MIT License
Classifier: Operating System :: OS Independent
Classifier: Programming Language :: Python :: 3
Requires-Python: >=3.7
